vanilla_registries/__init__.py
vanilla_registries/examples/pack/beet.yaml
vanilla_registries/examples/pack/demo.py
vanilla_registries/main.py
vanilla_registries-0.3.0.dist-info/LICENSE
vanilla_registries-0.3.0.dist-info/METADATA
vanilla_registries-0.3.0.dist-info/WHEEL
vanilla_registries-0.3.0.dist-info/RECORD
